<?xml version="1.0" encoding="utf-8"?>
<odoo>
    <data>
        <record id="view_order_form_inherit_disable_pricelist" model="ir.ui.view">
            <field name="name">sale.order.form.pricelist.readonly</field>
            <field name="model">sale.order</field>
            <field name="inherit_id" ref="sale.view_order_form"/>
            <field name="arch" type="xml">
                <xpath expr="//field[@name='pricelist_id']" position="attributes">
                    <attribute name="readonly">1</attribute>
                    <attribute name="groups">sales_team.group_sale_manager</attribute>
                </xpath>
                <xpath expr="//field[@name='payment_term_id']" position="attributes">
                    <attribute name="readonly">0</attribute>
                </xpath>
            </field>
        </record>
    </data>
        
</odoo>
